WeatherQualityCSB/__init__.py
WeatherQualityCSB/validations.py
WeatherQualityCSB/weather_quality.py
tests/__init__.py
tests/test_validations.py
WeatherQualityCSB-0.1.dist-info/LICENSE
WeatherQualityCSB-0.1.dist-info/METADATA
WeatherQualityCSB-0.1.dist-info/WHEEL
WeatherQualityCSB-0.1.dist-info/top_level.txt
WeatherQualityCSB-0.1.dist-info/RECORD
