Metadata-Version: 2.1
Name: WeatherQualityCSB
Version: 0.1
Summary: A utility to fetch weather quality data from the CSB website.
Home-page: https://github.com/melihoverflow5/WeatherQualityCSB
Author: melihoverflow5
Author-email: melihtaskin@pm.me
Classifier: Programming Language :: Python :: 3
Classifier: License :: OSI Approved :: MIT License
Classifier: Operating System :: OS Independent
Requires-Python: >=3.6
License-File: LICENSE
Requires-Dist: pytest
Requires-Dist: selenium
Requires-Dist: tqdm
